gembaface/__init__.py
gembaface/gembaface.py
gembaface-0.3.13.1.dist-info/DESCRIPTION.rst
gembaface-0.3.13.1.dist-info/METADATA
gembaface-0.3.13.1.dist-info/RECORD
gembaface-0.3.13.1.dist-info/WHEEL
gembaface-0.3.13.1.dist-info/metadata.json
gembaface-0.3.13.1.dist-info/top_level.txt
