Metadata-Version: 2.0
Name: gembaface
Version: 0.3.13.1
Summary: Simple client for GembaFace services
Home-page: UNKNOWN
Author: UNKNOWN
Author-email: UNKNOWN
License: UNKNOWN
Platform: UNKNOWN
Requires-Dist: requests
